README.md
setup.py
UliAcceleration/__init__.py
UliAcceleration.egg-info/PKG-INFO
UliAcceleration.egg-info/SOURCES.txt
UliAcceleration.egg-info/dependency_links.txt
UliAcceleration.egg-info/top_level.txt
UliAcceleration/SignalProcessing/SlidingWindow.py
UliAcceleration/SignalProcessing/__init__.py