Metadata-Version: 1.1
Name: UliAcceleration
Version: 0.1
Summary: Numba-Accelerated tools for signal processing and engineering
Home-page: https://techoverflow.net/
Author: Uli Köhler
Author-email: ukoehler@techoverflow.net
License: Apache License v2.0
Platform: any
Classifier: Development Status :: 4 - Beta
Classifier: Intended Audience :: Developers
Classifier: Intended Audience :: Science/Research
Classifier: Intended Audience :: Education
Classifier: Intended Audience :: Information Technology
Classifier: License :: DFSG approved
Classifier: License :: OSI Approved :: Apache Software License
Classifier: Programming Language :: Python
Classifier: Programming Language :: Python :: 3
Classifier: Topic :: Scientific/Engineering
Classifier: Topic :: Scientific/Engineering :: Information Analysis
Classifier: Topic :: Scientific/Engineering :: Physics
Requires: numpy (>= 1.5)
Requires: scipy (>= 0.5)
Requires: toolz (>= 0.5)
Requires: numba (>= 0.40)
Requires: UliEngineering (>= 0.1.1)
